configator/__init__.py
configator/create_actions_config.py
configator/create_gatorgradle_yml.py
configator/generate_build_gradle.py
configator/main.py
pyconfigator-1.0.3.dist-info/entry_points.txt
pyconfigator-1.0.3.dist-info/LICENSE
pyconfigator-1.0.3.dist-info/WHEEL
pyconfigator-1.0.3.dist-info/METADATA
pyconfigator-1.0.3.dist-info/RECORD
