Metadata-Version: 2.1
Name: pyconfigator
Version: 1.0.3
Summary: A Configuration File Generator for GatorGradle
License: MIT
Author: Kyrie Doniz
Requires-Python: >=3.7,<4.0
Classifier: License :: OSI Approved :: MIT License
Classifier: Programming Language :: Python :: 3
Classifier: Programming Language :: Python :: 3.7
Classifier: Programming Language :: Python :: 3.8
Classifier: Programming Language :: Python :: 3.9
Requires-Dist: typer (>=0.4.0,<0.5.0)
